[
  {
    "type": "file",
    "name": "index",
    "label": "面试准备总览"
  },
  {
    "type": "dir",
    "name": "process",
    "label": "面试流程"
  },
  {
    "type": "dir",
    "name": "resume",
    "label": "简历优化"
  },
  {
    "type": "dir",
    "name": "behavioral",
    "label": "行为面试"
  },
  {
    "type": "dir",
    "name": "puzzles",
    "label": "智力题"
  },
  {
    "type": "dir",
    "name": "hr",
    "label": "HR 面试"
  },
  {
    "type": "dir",
    "name": "experience",
    "label": "面经汇总"
  },
  {
    "type": "dir",
    "name": "review",
    "label": "复盘与评估"
  }
]
