[
  { "type": "file", "name": "flow", "label": "Spring MVC 请求处理流程" },
  { "type": "file", "name": "dispatcher-servlet", "label": "DispatcherServlet 源码" },
  { "type": "file", "name": "handler-mapping", "label": "HandlerMapping 与 Handler" },
  { "type": "file", "name": "interceptor-filter", "label": "拦截器 vs 过滤器" },
  { "type": "file", "name": "param-binding", "label": "参数绑定" },
  { "type": "file", "name": "view-resolver", "label": "视图解析与视图技术" },
  { "type": "file", "name": "exception-handler", "label": "异常处理" },
  { "type": "file", "name": "file-upload", "label": "文件上传与下载" },
  { "type": "file", "name": "restful", "label": "REST 设计" }
]
