[
    { "type": "file", "name": "redis-big-key", "label": "Redis 大 key 发现与解决方案" },
    { "type": "file", "name": "redis-hot-key", "label": "Redis hot key 发现与处理" },
    { "type": "file", "name": "redis-pipeline", "label": "Redis 管道（Pipeline）与批量操作" },
    { "type": "file", "name": "redis-memory", "label": "Redis 内存碎片与内存优化" },
    { "type": "file", "name": "redis-persistence", "label": "Redis 持久化策略选择：RDB vs AOF vs 混合持久化" },
    { "type": "file", "name": "redis-cluster-optimize", "label": "Redis 集群优化：槽迁移与热点扩容" }
]